{
	"categories": [
		{
			"name": "一般检查",
			"id": "GeneralInspection",
			"experiments": [
				{
					"name": "外观检查",
					"id": "VisualInspection",
					"output_items": [
						{
							"en": "",
							"cn": "目测检查充电机（含充电连接装置）的外壳应平整，无明显凹凸痕、划伤、变形等缺陷；表面涂镀层应均匀，无脱落；内部零部件（包括连接装置内触头）应紧固可靠，无锈蚀、毛刺、裂纹等缺陷和损伤。"
						}
					]
				},
				{
					"name": "标志检查",
					"id": "SignTest",
					"output_items": [
						{
							"en": "",
							"cn": "目测检查充电机铭牌位置和内容的正确性与完整性，名牌内容应符合NB/T 33001-2018中8.1.1的规定。目测检查充电机上接线、接地及安全标志的正确性与完整性。通过观察并用一块浸透蒸馏水的脱脂棉在约15s内擦拭15个来回，随后用一块浸透汽油的脱脂棉在约15s内擦拭15个来回，试验期间应用约2N/cm2的压力将脱脂棉压在标志上。试验后，标志仍应易于辨认。"
						}
					]
				},
				{
					"name": "基本构成检查",
					"id": "BasicCompositionTest",
					"output_items": [
						{
							"en": "",
							"cn": "打开充电机门，目测检查充电机的基本构成应包括动力电源输入、功率变换单元、输出开关单元、充电电缆和车辆插头、控制电源、充电控制单元、人机交互单元，宜包括计量等功能单元。"
						}
					]
				},
				{
					"name": "机械开关设备检查",
					"id": "MechanicalSwitchgearInspection",
					"output_items": [
						{
							"en": "",
							"cn": "开关和隔离开关：检查充电机的开关和隔离开关应符合GB/T 18487.1-2015中10.2.1的规定或具备对应的证明材料。 接触器：检查充电机的交流/直流接触器应符合GB/T 18487.1-2015中10.2.2的规定或具备对应的证明材料。 断路器：检查充电机的断路器应符合GB/T 18487.1-2015中10.2.3的规定或具备对应的证明材料。 继电器：检查充电机的继电器应符合GB/T 18487.1-2015中10.2.4的规定或具备对应的证明材料。"
						}
					]
				},
				{
					"name": "防雷措施检查",
					"id": "InspectionOfLightningProtectionMeasures",
					"output_items": [
						{
							"en": "",
							"cn": "检查充电机应采取避雷防护措施，且符合GB/T 18487.1-2015中11.7的规定。"
						}
					]
				},
				{
					"name": "防盗措施检查",
					"id": "TestTheAntiTheftMeasures",
					"output_items": [
						{
							"en": "",
							"cn": "对于户外型充电机，检查其应具有防盗措施，如防盗锁和防盗螺钉等，且产品安装说明书中应有相关要求。"
						}
					]
				},
				{
					"name": "供电设备断电控制功能检查",
					"id": "InspectionOfPowerOffControlFunctionOfPowerSupplyEquipment",
					"output_items": [
						{
							"en": "",
							"cn": "检查充电机应具备供电设备控制断电功能。"
						}
					]
				},
				{
					"name": "锁紧装置检查",
					"id": "LockingDeviceInspection",
					"output_items": [
						{
							"en": "",
							"cn": "检查充电机应具备锁紧装置。"
						}
					]
				}
			]
		},
		{
			"name": "功能试验",
			"id": "FunctionTest",
			"experiments": [
				{
					"name": "充电控制功能试验",
					"id": "ChargingControlFunctionTest",
					"output_items": [
						{
							"cn": "将充电机连接试验系统，检查充电机应能根据车辆电池管理系统模拟软件提供的数据动态调整充电输出，并根据情况执行相应动作，控制充电过程且自动完成充电。",
							"en": ""
						},
						{
							"cn": "对于具备手动充电控制功能的充电机，连接试验系统，在没有连接上层监控管理系统和车辆的情况下，检查充电机应由手动设定充电参数，并实施充电启停操作，完成充电过程。",
							"en": ""
						}
					]
				},
				{
					"name": "通信功能试验",
					"id": "CommunicationFunctionTest",
					"output_items": [
						{
							"cn": "对于具备与厂家指定的上级监控系统或运营管理系统通信的充电机，连接试验系统，在充电过程中，检查充电机应能按照约定的协议要求进行通信。",
							"en": ""
						}
					]
				},
				{
					"name": "绝缘检测功能试验1",
					"id": "InsulationDetectionSub1",
					"output_items": [
						{
							"cn": "不应进行自检且未收到CRM报文。",
							"en": ""
						},
						{
							"cn": "应有告警提示。",
							"en": ""
						},
						{
							"cn": "外侧电压",
							"en": ""
						},
						{
							"cn": "CRM报文",
							"en": ""
						},
						{
							"cn": "是否告警",
							"en": ""
						}
					]
				},
				{
					"name": "绝缘检测功能试验2",
					"id": "InsulationDetectionSub2",
					"output_items": [
						{
							"cn": "绝缘检测的输出电压为车辆通信握手报文内的最高允许充电总电压和充电机额定电压二者中的较小值。",
							"en": ""
						},
						{
							"cn": "充电机额定电压",
							"en": ""
						},
						{
							"cn": "最高允许充电总电压",
							"en": ""
						},
						{
							"cn": "绝缘检测电压值",
							"en": ""
						}
					]
				},
				{
					"name": "绝缘检测功能试验3",
					"id": "InsulationDetectionSub3",
					"output_items": [
						{
							"cn": "宜进行绝缘异常提示",
							"en": ""
						},
						{
							"cn": "允许充电。",
							"en": ""
						},
						{
							"cn": "绝缘检测完成后，泄放回路应在充电连接器断开后1s内将供电接口电压降到60VDC以下。",
							"en": ""
						},
						{
							"cn": "测试电阻",
							"en": ""
						},
						{
							"cn": "前端电压开始下降电压时刻",
							"en": ""
						},
						{
							"cn": "前端电压下降至60V以下时刻",
							"en": ""
						},
						{
							"cn": "是否允许充电",
							"en": ""
						},
						{
							"cn": "是否有告警提示",
							"en": ""
						}
					]
				},
				{
					"name": "绝缘检测功能试验4",
					"id": "InsulationDetectionSub4",
					"output_items": [
						{
							"cn": "宜进行绝缘异常提示",
							"en": ""
						},
						{
							"cn": "允许充电。",
							"en": ""
						},
						{
							"cn": "绝缘检测完成后，泄放回路应在充电连接器断开后1s内将供电接口电压降到60VDC以下。",
							"en": ""
						},
						{
							"cn": "测试电阻",
							"en": ""
						},
						{
							"cn": "前端电压开始下降电压时刻",
							"en": ""
						},
						{
							"cn": "前端电压下降至60V以下时刻",
							"en": ""
						},
						{
							"cn": "是否允许充电",
							"en": ""
						},
						{
							"cn": "是否有告警提示",
							"en": ""
						}
					]
				},
				{
					"name": "绝缘检测功能试验5",
					"id": "InsulationDetectionSub5",
					"output_items": [
						{
							"cn": "宜进行绝缘异常提示",
							"en": ""
						},
						{
							"cn": "允许充电。",
							"en": ""
						},
						{
							"cn": "绝缘检测完成后，泄放回路应在充电连接器断开后1s内将供电接口电压降到60VDC以下。",
							"en": ""
						},
						{
							"cn": "测试电阻",
							"en": ""
						},
						{
							"cn": "前端电压开始下降电压时刻",
							"en": ""
						},
						{
							"cn": "前端电压下降至60V以下时刻",
							"en": ""
						},
						{
							"cn": "是否允许充电",
							"en": ""
						},
						{
							"cn": "是否有告警提示",
							"en": ""
						}
					]
				},
				{
					"name": "绝缘检测功能试验6",
					"id": "InsulationDetectionSub6",
					"output_items": [
						{
							"cn": "宜进行绝缘异常提示",
							"en": ""
						},
						{
							"cn": "允许充电。",
							"en": ""
						},
						{
							"cn": "绝缘检测完成后，泄放回路应在充电连接器断开后1s内将供电接口电压降到60VDC以下。",
							"en": ""
						},
						{
							"cn": "测试电阻",
							"en": ""
						},
						{
							"cn": "前端电压开始下降电压时刻",
							"en": ""
						},
						{
							"cn": "前端电压下降至60V以下时刻",
							"en": ""
						},
						{
							"cn": "是否允许充电",
							"en": ""
						},
						{
							"cn": "是否有告警提示",
							"en": ""
						}
					]
				},
				{
					"name": "绝缘检测功能试验7",
					"id": "InsulationDetectionSub7",
					"output_items": [
						{
							"cn": "有绝缘故障告警。",
							"en": ""
						},
						{
							"cn": "不允许充电。",
							"en": ""
						},
						{
							"cn": "绝缘检测完成后，泄放回路应在充电连接器断开后1s内将供电接口电压降到60VDC以下。",
							"en": ""
						},
						{
							"cn": "测试电阻",
							"en": ""
						},
						{
							"cn": "前端电压开始下降电压时刻",
							"en": ""
						},
						{
							"cn": "前端电压下降至60V以下时刻",
							"en": ""
						},
						{
							"cn": "是否允许充电",
							"en": ""
						},
						{
							"cn": "是否有告警提示",
							"en": ""
						}
					]
				},
				{
					"name": "绝缘检测功能试验8",
					"id": "InsulationDetectionSub8",
					"output_items": [
						{
							"cn": "有绝缘故障告警。",
							"en": ""
						},
						{
							"cn": "不允许充电。",
							"en": ""
						},
						{
							"cn": "绝缘检测完成后，泄放回路应在充电连接器断开后1s内将供电接口电压降到60VDC以下。",
							"en": ""
						},
						{
							"cn": "测试电阻",
							"en": ""
						},
						{
							"cn": "前端电压开始下降电压时刻",
							"en": ""
						},
						{
							"cn": "前端电压下降至60V以下时刻",
							"en": ""
						},
						{
							"cn": "是否允许充电",
							"en": ""
						},
						{
							"cn": "是否有告警提示",
							"en": ""
						}
					]
				},
				{
					"name": "直流输出回路短路检测功能试验",
					"id": "ShortCircuitDetectionFunctionTestOfDcOutputCircuit",
					"output_items": [
						{
							"cn": "是否绝缘检测",
							"en": ""
						},
						{
							"cn": "是否告警提示",
							"en": ""
						}
					]
				},
				{
					"name": "车辆插头锁止功能试验",
					"id": "VehicleConnectorLockingFunctionTest",
					"output_items": [
						{
							"cn": "检测点1电压为4.01V,施加200N的拔出外力，连接没有断开，且锁止装置没有损坏；",
							"en": ""
						},
						{
							"cn": "电子锁止装置对机械锁止装置具有联锁效果。当电子锁未可靠锁止时，充电机不允许充电。在整个充电过程中（包括绝缘检测过程），充电机电子锁止可靠锁止，不允许带电解锁且不能由人手直接操作解锁；",
							"en": ""
						},
						{
							"cn": "模拟故障不能继续充电、充电完成时，在解除电子锁时车辆接口电压降至60VDC以下；",
							"en": ""
						},
						{
							"cn": "电子锁装置具备急解锁功能。",
							"en": ""
						}
					]
				},
				{
					"name": "预充电功能试验",
					"id": "PreChargeFunctionTest",
					"output_items": [
						{
							"cn": "充电机在其输出电压比接触器外端电压低(1V~10V)时，闭合K1和K2。",
							"en": ""
						},
						{
							"cn": "外端测量电压",
							"en": ""
						},
						{
							"cn": "报文电池电压",
							"en": ""
						},
						{
							"cn": "误差",
							"en": ""
						},
						{
							"cn": "K1K2闭合时外端电压",
							"en": ""
						},
						{
							"cn": "K1K2闭合时输出电压",
							"en": ""
						}
					]
				},
				{
					"name": "显示功能试验",
					"id": "DisplayFunctionTest",
					"output_items": [
						{
							"cn": "将充电机连接试验系统，模拟待机状态、充电状态、故障或告警状态等，检查充电机的显示信息或状态应符合NB/T 33001-2018中6.7.1的规定，且显示字符清晰、完整，没有缺损。",
							"en": ""
						},
						{
							"cn": "对于具备手动充电控制功能的充电机，检查应能显示人工输入信息。",
							"en": ""
						}
					]
				},
				{
					"name": "输入功能试验",
					"id": "InputFunctionTest",
					"output_items": [
						{
							"cn": "对于具备手动充电控制功能的充电机，连接试验系统，设置充电机充电参数，检查充电机应能正确进入充电过程并执行设置操作；在充电过程中，模拟进行启停操作，检查充电机应能正确启动或停止充电。",
							"en": ""
						}
					]
				},
				{
					"name": "计量功能试验",
					"id": "MeteringFunctionTest",
					"output_items": [
						{
							"cn": "对于安装有电能表的充电机，检查充电机电能计量功能应符合GB/T 29318 的规定。",
							"en": ""
						}
					]
				},
				{
					"name": "急停功能试验",
					"id": "EmergencyStopFunctionTest",
					"output_items": [
						{
							"cn": "检查充电机应安装急停装置，且具备防止误操作的防护措施。",
							"en": ""
						},
						{
							"cn": "对于一体式充电机，将充电机连接试验系统，在充电过程中，模拟启动急停装置，检查充电机应能同时切断充电机的动力电源输入和直流输出。",
							"en": ""
						},
						{
							"cn": "对于分体式充电机，将充电机连接试验系统，在充电过程中，模拟启动急停装置，检查充电机应能切断相应充电终端的直流输出，也可同时切断充电机的动力电源输入和直流输出。",
							"en": ""
						}
					]
				}
			]
		},
		{
			"name": "安全要求试验",
			"id": "FunctionTest",
			"experiments": [
				{
					"name": "输入过压保护试验",
					"id": "InputOvervoltageProtectionTest",
					"output_items": [
						{
							"cn": "保护动作值",
							"en": ""
						},
						{
							"cn": "是否告警",
							"en": ""
						}
					]
				},
				{
					"name": "输入欠压保护试验",
					"id": "InputUndervoltageProtectionTest",
					"output_items": [
						{
							"cn": "保护动作值",
							"en": ""
						},
						{
							"cn": "是否告警",
							"en": ""
						}
					]
				},
				{
					"name": "输出过压保护试验",
					"id": "OutputOvervoltageProtectionTest",
					"output_items": [
						{
							"cn": "充电桩最高允许充电总电",
							"en": ""
						},
						{
							"cn": "输出过压保护动作值",
							"en": ""
						},
						{
							"cn": "过压后输出电压",
							"en": ""
						},
						{
							"cn": "过压后输出电流",
							"en": ""
						},
						{
							"cn": "是否告警提示",
							"en": ""
						}
					]
				},
				{
					"name": "输出短路保护试验",
					"id": "OutputShortCircuitProtectionTest",
					"output_items": [
						{
							"cn": "短路前输出电压",
							"en": ""
						},
						{
							"cn": "短路前输出电流",
							"en": ""
						},
						{
							"cn": "短路后输出电压",
							"en": ""
						},
						{
							"cn": "短路后输出电流",
							"en": ""
						},
						{
							"cn": "是否告警提示",
							"en": ""
						}
					]
				},
				{
					"name": "过温保护试验",
					"id": "OverTemperatureProtectionTest",
					"output_items": [
						{
							"cn": "过温前输出电压",
							"en": ""
						},
						{
							"cn": "过温前输出电流",
							"en": ""
						},
						{
							"cn": "过温前输出功率",
							"en": ""
						},
						{
							"cn": "过温后输出电压",
							"en": ""
						},
						{
							"cn": "过温后输出电流",
							"en": ""
						},
						{
							"cn": "过温后输出功率",
							"en": ""
						},
						{
							"cn": "是否告警提示",
							"en": ""
						}
					]
				},
				{
					"name": "开门保护试验",
					"id": "DoorOpeningProtectionTest",
					"output_items": [
						{
							"cn": "在充电前，打开充电机门，检查充电机，应无法启动充电。",
							"en": ""
						},
						{
							"cn": "在充电过程中，模拟门打开，充电机应切断相应部分的电源输入或输出。",
							"en": ""
						}
					]
				},
				{
					"name": "启动急停装置试验",
					"id": "TestOfStartupEmergencyStopDevice",
					"output_items": [
						{
							"cn": "充电机在100ms内断开K1、K2。",
							"en": ""
						},
						{
							"cn": "电子锁解锁时车辆接口电压不应超过60V。",
							"en": ""
						},
						{
							"cn": "急停故障时刻",
							"en": ""
						},
						{
							"cn": "K1K2断开时刻",
							"en": ""
						},
						{
							"cn": "K1K2断开时间",
							"en": ""
						},
						{
							"cn": "电子锁解锁时车辆接口电压",
							"en": ""
						}
					]
				},
				{
					"name": "输入电流过冲试验",
					"id": "InputCurrentOvershootTest",
					"output_items": [
						{
							"cn": "额定峰值电流",
							"en": ""
						},
						{
							"cn": "过冲峰值电流",
							"en": ""
						},
						{
							"cn": "百分比",
							"en": ""
						}
					]
				},
				{
					"name": "蓄电池反接试验",
					"id": "BatteryReverseConnectionTest",
					"output_items": [
						{
							"cn": "是否允许充电",
							"en": ""
						},
						{
							"cn": "是否告警提示",
							"en": ""
						}
					]
				},
				{
					"name": "防逆流功能试验",
					"id": "AntiReverseFlowFunctionTest",
					"output_items": [
						{
							"cn": "当前输出电压",
							"en": ""
						},
						{
							"cn": "外侧电压",
							"en": ""
						},
						{
							"cn": "反向电流",
							"en": ""
						}
					]
				},
				{
					"name": "接触器粘连试验",
					"id": "ContactorStickingTest",
					"output_items": [
						{
							"cn": "是否绝缘检测",
							"en": ""
						},
						{
							"cn": "是否告警提示",
							"en": ""
						}
					]
				}
			]
		},
		{
			"name": "充电模式和连接方式检查",
			"id": "ChargingModeAndConnectionTest",
			"experiments": [
				{
					"name": "充电模式和连接方式检查",
					"id": "ChargingModeAndConnectionTest",
					"output_items": [
						{
							"cn": "",
							"en": ""
						}
					]
				}
			]
		},
		{
			"name": "充电连接装置及电缆检查",
			"id": "InspectionOfChargingConnectionDeviceAndCable",
			"experiments": [
				{
					"name": "充电连接装置检查",
					"id": "InspectionOfChargingConnectionDevice",
					"output_items": [
						{
							"cn": "检查充电机所配置的充电用连接装置应具备符合GB/T 20234.1-2015、GB/T 20234.3-2015规定的证明材料，或者按照GB/T 34657.1-2017中6.2规定的方法对车辆插头的结构尺寸、插头空间尺寸进行复合。",
							"en": ""
						}
					]
				},
				{
					"name": "电缆管理及贮存检查",
					"id": "CableManagementAndStorageInspection",
					"output_items": [
						{
							"cn": "检查充电机应随桩配置车辆插头贮存装置，该装置可以与充电机分离或固定在充电机上。在未使用车辆插头时，检查车辆插头应存放在地面上方0.5 m~1.5m处（除地面安装设备）；对采用长度超过7.5m的电缆的充电机检查自由电缆长度不应超过7.5m。对于未在充电机本体上设置车辆插头贮存装置，检查产品说明书应有外置车辆插头贮存装置的安装位置相关说明，应随桩配置车辆插头贮存装置。",
							"en": ""
						}
					]
				}
			]
		},
		{
			"name": "充电阶段检验",
			"id": "ChargingPhaseInspection",
			"experiments": [
				{
					"name": "DP3001",
					"id": "DP3001",
					"output_items": [
						{
							"cn": "检查充电机使用传输协议接收BCS正确性",
							"en": ""
						},
						{
							"cn": "检查CCS报文发送起始条件正确性",
							"en": ""
						},
						{
							"cn": "检查CCS报文ID正确性",
							"en": ""
						},
						{
							"cn": "检查CCS报文数据长度正确性",
							"en": ""
						},
						{
							"cn": "检查CCS报文发送周期正确性",
							"en": ""
						},
						{
							"cn": "充电机传输协议功能接收BCS报文",
							"en": ""
						},
						{
							"cn": "充电机发送SPN2830=0xAA的CRO报文",
							"en": ""
						},
						{
							"cn": "充电机50ms的周期发送CCS报文，报文格式、内容和周期GB/T 27930—2015中9.3和10.3.3的要求，报文长度7个字节",
							"en": ""
						}
					]
				},
				{
					"name": "DP3002",
					"id": "DP3002",
					"output_items": [
						{
							"cn": "检查充电机接收BMS请求发送消息RTS报文正确性（BMV报文）",
							"en": ""
						},
						{
							"cn": "检查充电机接收BMS请求发送消息RTS报文正确性（BMT报文）",
							"en": ""
						},
						{
							"cn": "检查充电机接收BMS请求发送消息RTS报文正确性（BSP报文）",
							"en": ""
						}
					]
				},
				{
					"name": "DP3003",
					"id": "DP3003",
					"output_items": [
						{
							"cn": "1 检查充电机接收单体动力蓄电池电压异常的BSM（SPN3090=01或者SPN3090=10）的响应",
							"en": ""
						},
						{
							"cn": "1.1 检查CST报文ID正确性",
							"en": ""
						},
						{
							"cn": "1.2 检查CST报文数据长度正确性",
							"en": ""
						},
						{
							"cn": "1.3 检查CST报文发送周期正确性",
							"en": ""
						},
						{
							"cn": "1.4 检查CST报文发送内容正确性",
							"en": ""
						},
						{
							"cn": "2 检查充电机接收整车动力蓄电池荷电状态SOC异常的BSM（SPN3091=01或者SPN3091=10）报文的响应",
							"en": ""
						},
						{
							"cn": "2.1 检查CST报文ID正确性",
							"en": ""
						},
						{
							"cn": "2.2 检查CST报文数据长度正确性",
							"en": ""
						},
						{
							"cn": "2.3 检查CST报文发送周期正确性",
							"en": ""
						},
						{
							"cn": "2.4 检查CST报文发送内容正确性",
							"en": ""
						},
						{
							"cn": "3 检查充电机接收动力蓄电池充电电流异常的BSM（SPN3092=01）报文的响应",
							"en": ""
						},
						{
							"cn": "3.1 检查CST报文ID正确性",
							"en": ""
						},
						{
							"cn": "3.2 检查CST报文数据长度正确性",
							"en": ""
						},
						{
							"cn": "3.3 检查CST报文发送周期正确性",
							"en": ""
						},
						{
							"cn": "3.4 检查CST报文发送内容正确性",
							"en": ""
						},
						{
							"cn": "4 检查充电机接收动力蓄电池温度异常的BSM（SPN3093=01）报文的响应",
							"en": ""
						},
						{
							"cn": "4.1 检查CST报文ID正确性",
							"en": ""
						},
						{
							"cn": "4.2 检查CST报文数据长度正确性",
							"en": ""
						},
						{
							"cn": "4.3 检查CST报文发送周期正确性",
							"en": ""
						},
						{
							"cn": "4.4 检查CST报文发送内容正确性",
							"en": ""
						},
						{
							"cn": "5 检查充电机接收动力蓄电池绝缘状态异常的BSM（SPN3094=01）报文的响应",
							"en": ""
						},
						{
							"cn": "5.1 检查CST报文ID正确性",
							"en": ""
						},
						{
							"cn": "5.2 检查CST报文数据长度正确性",
							"en": ""
						},
						{
							"cn": "5.3 检查CST报文发送周期正确性",
							"en": ""
						},
						{
							"cn": "5.4 检查CST报文发送内容正确性",
							"en": ""
						},
						{
							"cn": "6 检查充电机接收动力蓄电池输出连接器连接状态异常的BSM（SPN3095=01）报文的响应",
							"en": ""
						},
						{
							"cn": "6.1 检查CST报文ID正确性",
							"en": ""
						},
						{
							"cn": "6.2 检查CST报文数据长度正确性",
							"en": ""
						},
						{
							"cn": "6.3 检查CST报文发送周期正确性",
							"en": ""
						},
						{
							"cn": "6.4 检查CST报文发送内容正确性",
							"en": ""
						},
						{
							"cn": "a）充电机发送CCS报文，同时停止电力输出，并10ms的周期发送CST报文，报文格式、内容和周期GB/T 27930—2015中9.3和10.3.9的要求，报文长度4个字节。",
							"en": ""
						},
						{
							"cn": "b）充电机发送CCS报文，同时停止电力输出，并10 ms的周期发送CST报文，报文格式、内容和周期GB/T 27930—2015中9.3和10.3.9的要求，报文长度4个字节。",
							"en": ""
						},
						{
							"cn": "c）充电机发送CCS报文，同时停止电力输出，并10 ms的周期发送CST报文，报文格式、内容和周期GB/T 27930—2015中9.3和10.3.9的要求，报文长度4个字节。",
							"en": ""
						},
						{
							"cn": "d）充电机发送CCS报文，同时停止电力输出，并10 ms的周期发送CST报文，报文格式、内容和周期GB/T 27930—2015中9.3和10.3.9的要求，报文长度4个字节。",
							"en": ""
						},
						{
							"cn": "e）充电机发送CCS报文，同时停止电力输出，并10 ms的周期发送CST报文，报文格式、内容和周期GB/T 27930—2015中9.3和10.3.9的要求，报文长度4个字节。",
							"en": ""
						},
						{
							"cn": "f）充电机发送CCS报文，同时停止电力输出，并10 ms的周期发送CST报文，报文格式、内容和周期GB/T 27930—2015中9.3和10.3.9的要求，报文长度4个字节。",
							"en": ""
						}
					]
				},
				{
					"name": "DP3004",
					"id": "DP3004",
					"output_items": [
						{
							"cn": "1 检查充电机接收动力蓄电池充电电流不可信状态的BSM（SPN3092=10）报文处理正确性",
							"en": ""
						},
						{
							"cn": "1.1 检查CCS报文ID正确性",
							"en": ""
						},
						{
							"cn": "1.2 检查CCS报文数据长度正确性",
							"en": ""
						},
						{
							"cn": "1.3 检查CCS报文发送周期正确性",
							"en": ""
						},
						{
							"cn": "2 检查充电机接收动力蓄电池温度不可信状态的BSM（SPN3093=10）报文处理正确性",
							"en": ""
						},
						{
							"cn": "2.1 检查CCS报文ID正确性",
							"en": ""
						},
						{
							"cn": "2.2 检查CCS报文数据长度正确性",
							"en": ""
						},
						{
							"cn": "2.3 检查CCS报文发送周期正确性",
							"en": ""
						},
						{
							"cn": "3 检查充电机接收动力蓄电池绝缘状态不可信状态的BSM（SPN3094=10）",
							"en": ""
						},
						{
							"cn": "3.1 检查CCS报文ID正确性",
							"en": ""
						},
						{
							"cn": "3.2 检查CCS报文数据长度正确性",
							"en": ""
						},
						{
							"cn": "3.3 检查CCS报文发送周期正确性",
							"en": ""
						},
						{
							"cn": "4 检查充电机接收动力蓄电池输出连接器连接状态不可信状态的BSM（SPN3095=10）报文处理正确性",
							"en": ""
						},
						{
							"cn": "4.1 检查CCS报文ID正确性",
							"en": ""
						},
						{
							"cn": "4.2 检查CCS报文数据长度正确性",
							"en": ""
						},
						{
							"cn": "4.3 检查CCS报文发送周期正确性",
							"en": ""
						},
						{
							"cn": "a）按BMS需求输出，同时50 ms的周期发送CCS报文，报文格式、内容和周期GB/T 27930—2015中9.3和10.3.3的要求，报文长度7个字节。",
							"en": ""
						},
						{
							"cn": "b）按BMS需求输出，同时50 ms的周期发送CCS报文，报文格式、内容和周期GB/T 27930—2015中9.3和10.3.3的要求，报文长度7个字节。",
							"en": ""
						},
						{
							"cn": "c）按BMS需求输出，同时50 ms的周期发送CCS报文，报文格式、内容和周期GB/T 27930—2015中9.3和10.3.3的要求，报文长度7个字节。",
							"en": ""
						},
						{
							"cn": "d）按BMS需求输出，同时50 ms的周期发送CCS报文，报文格式、内容和周期GB/T 27930—2015中9.3和10.3.3的要求，报文长度7个字节。",
							"en": ""
						}
					]
				},
				{
					"name": "DP3005",
					"id": "DP3005",
					"output_items": [
						{
							"cn": "1 检查充电暂停充电过程中通信状态",
							"en": ""
						},
						{
							"cn": "2 检查暂停充电过程中充电机输出状态",
							"en": ""
						},
						{
							"cn": "3 检查充电机恢复充电正确性",
							"en": ""
						},
						{
							"cn": "4 检查CST发送起始条件正确性",
							"en": ""
						},
						{
							"cn": "5 检查CST报文ID正确性",
							"en": ""
						},
						{
							"cn": "6 检查CST报文数据长度正确性",
							"en": ""
						},
						{
							"cn": "7 检查CST报文发送周期正确性",
							"en": ""
						},
						{
							"cn": "8 检查CST报文发送内容正确性",
							"en": ""
						},
						{
							"cn": "1）充电机 暂停输出电流，测试系统和充电机按充电流程正常通信；",
							"en": ""
						},
						{
							"cn": "2）等待时间10 min内，接收到测试系统中报文SPN3090—SPN3095均为00（电池状态正常），且SPN3096为01（允许充电）时，充电机恢复充电且冲击电流满足GB/T 18487.1—2015中9.7要求；",
							"en": ""
						},
						{
							"cn": "3）等待时间ms，充电机中止充电，按10 ms的周期发送CST报文，报文格式、内容和周期",
							"en": ""
						}
					]
				},
				{
					"name": "DP3006",
					"id": "DP3006",
					"output_items": [
						{
							"cn": "1 检查充电机接收BMS中止充电原因",
							"en": ""
						},
						{
							"cn": "1.1 检查CST报文ID正确性",
							"en": ""
						},
						{
							"cn": "1.2 检查CST报文数据长度正确性",
							"en": ""
						},
						{
							"cn": "1.3 检查CST报文发送周期正确性",
							"en": ""
						},
						{
							"cn": "1.4 检查CST报文发送内容正确性",
							"en": ""
						},
						{
							"cn": "2 检查充电机接收BMS中止充电故障原因",
							"en": ""
						},
						{
							"cn": "2.1 检查CST报文ID正确性",
							"en": ""
						},
						{
							"cn": "2.2 检查CST报文数据长度正确性",
							"en": ""
						},
						{
							"cn": "2.3 检查CST报文发送周期正确性",
							"en": ""
						},
						{
							"cn": "2.4 检查CST报文发送内容正确性",
							"en": ""
						},
						{
							"cn": "a）充电机接收到BST报文，发送CCS报文，10 ms的周期发送CST报文，报文格式、内容和周期GB/T 27930—2015中9.3和10.3.9的要求，报文长度4个字节，同时停止电力输出。",
							"en": ""
						},
						{
							"cn": "b）充电机接收到BST报文，发送CCS报文，10 ms的周期发送CST报文，报文格式、内容和周期GB/T 27930—2015中9.3和10.3.9的要求，报文长度4个字节，同时停止电力输出。",
							"en": ""
						}
					]
				},
				{
					"name": "DP3007",
					"id": "DP3007",
					"output_items": [
						{
							"cn": "1 检查CST报文ID正确性",
							"en": ""
						},
						{
							"cn": "2 检查CST报文数据长度正确性",
							"en": ""
						},
						{
							"cn": "3 检查CST报文发送周期正确性",
							"en": ""
						},
						{
							"cn": "4 检查CST报文发送内容正确性",
							"en": ""
						},
						{
							"cn": "1）充电机10ms的周期发送CST报文，报文格式、内容和周期GB/T 27930—2015 9.3和10.3.9的要求，报文长度4个字节，同时停止电力输出。",
							"en": ""
						}
					]
				},
				{
					"name": "DN3001",
					"id": "DN3001",
					"output_items": [
						{
							"cn": "1 检查充电机判断BCS报文超时时间",
							"en": ""
						},
						{
							"cn": "2 检查SPN3924=01的CEM报文正确性",
							"en": ""
						},
						{
							"cn": "3 检查CEM报文ID正确性",
							"en": ""
						},
						{
							"cn": "4 检查CEM报文发送周期正确性",
							"en": ""
						},
						{
							"cn": "5 检查CEM数据域正确性",
							"en": ""
						},
						{
							"cn": "6 检查CRO报文发送周期正确性",
							"en": ""
						},
						{
							"cn": "7 检查CRO报文发送ID正确性",
							"en": ""
						},
						{
							"cn": "8 检查CRO报文发送长度正确性",
							"en": ""
						},
						{
							"cn": "9 检查CRO报文发送数据域正确性",
							"en": ""
						},
						{
							"cn": "1）自首次发送SPN2830=0xAA的CRO报文起ms充电机250 ms的周期发送该报文，报文格式、内容和周期GBT 27930—2015中9.2和10.2.5的要求；",
							"en": ""
						},
						{
							"cn": "2）超过ms，充电机发送SPN3924=01的CEM报文，报文格式、内容和周期GBT 27930—2015中9.5和10.5.2的要求。",
							"en": ""
						}
					]
				},
				{
					"name": "DN3002",
					"id": "DN3002",
					"output_items": [
						{
							"cn": "1 检查充电机判断BCL报文超时时间",
							"en": ""
						},
						{
							"cn": "2 检查SPN3925=01的CEM报文正确性",
							"en": ""
						},
						{
							"cn": "3 检查CEM报文ID正确性",
							"en": ""
						},
						{
							"cn": "4 检查CEM报文发送周期正确性",
							"en": ""
						},
						{
							"cn": "5 检查CEM数据域正确性",
							"en": ""
						},
						{
							"cn": "6 检查CRO报文发送周期正确性",
							"en": ""
						},
						{
							"cn": "7 检查CRO报文发送ID正确性",
							"en": ""
						},
						{
							"cn": "8 检查CRO报文发送长度正确性",
							"en": ""
						},
						{
							"cn": "9 检查CRO报文发送数据域正确性",
							"en": ""
						},
						{
							"cn": "10 检查充电机使用传输协议接收BCS正确性",
							"en": ""
						},
						{
							"cn": "1）充电机传输协议功能接收BCS报文；",
							"en": ""
						},
						{
							"cn": "2）自首次发送SPN2830=0xAA的CRO报文起ms充电机250 ms的周期发送该报文，报文格式、内容和周期GBT 27930—2015中9.2和10.2.5的要求。",
							"en": ""
						},
						{
							"cn": "3）超过ms，充电机发送SPN3925=01的CEM报文，报文格式、内容和周期GBT 27930—2015中9.5和10.5.2的要求。",
							"en": ""
						}
					]
				},
				{
					"name": "DN3003",
					"id": "DN3003",
					"output_items": [
						{
							"cn": "1 检查充电机判断BCS报文超时时间",
							"en": ""
						},
						{
							"cn": "2 检查SPN3924=01的CEM报文正确性",
							"en": ""
						},
						{
							"cn": "3 检查CEM报文ID正确性",
							"en": ""
						},
						{
							"cn": "4 检查CEM报文发送周期正确性",
							"en": ""
						},
						{
							"cn": "5 检查CEM数据域正确性",
							"en": ""
						},
						{
							"cn": "6 检查CRO报文发送周期正确性",
							"en": ""
						},
						{
							"cn": "7 检查CRO报文发送ID正确性",
							"en": ""
						},
						{
							"cn": "8 检查CRO报文发送长度正确性",
							"en": ""
						},
						{
							"cn": "9 检查CRO报文发送数据域正确性",
							"en": ""
						},
						{
							"cn": "1）充电机使用传输协议功能接收BCS报文；",
							"en": ""
						},
						{
							"cn": "2）自首次发送SPN2830=0xAA的CRO报文起ms充电机250 ms的周期发送该报文，报文格式、内容和周期GBT 27930—2015中9.2和10.2.5的要求。",
							"en": ""
						},
						{
							"cn": "3）超过ms，充电机发送SPN3924=01的CEM报文，报文格式、内容和周期GBT 27930—2015中9.5和10.5.2的要求。",
							"en": ""
						}
					]
				},
				{
					"name": "DN3004",
					"id": "DN3004",
					"output_items": [
						{
							"cn": "1 检查充电机判断BCL超时时间长度",
							"en": ""
						},
						{
							"cn": "2 检查SPN3925=01的CEM报文正确性",
							"en": ""
						},
						{
							"cn": "3 检查CEM报文ID正确性",
							"en": ""
						},
						{
							"cn": "4 检查CEM报文发送周期正确性",
							"en": ""
						},
						{
							"cn": "5 检查CEM数据域正确性",
							"en": ""
						},
						{
							"cn": "6 检查CRO报文发送周期正确性",
							"en": ""
						},
						{
							"cn": "7 检查CRO报文发送ID正确性",
							"en": ""
						},
						{
							"cn": "8 检查CRO报文发送长度正确性",
							"en": ""
						},
						{
							"cn": "9 检查CRO报文发送数据域正确性",
							"en": ""
						},
						{
							"cn": "10 检查充电机使用传输协议接收BCS正确性",
							"en": ""
						},
						{
							"cn": "1）充电机传输协议功能接收BCS报文；",
							"en": ""
						},
						{
							"cn": "2）自首次发送SPN2830=0xAA的CRO报文起ms充电机250 ms的周期发送该报文，报文格式、内容和周期GBT 27930—2015中9.2和10.2.5的要求；",
							"en": ""
						},
						{
							"cn": "3）超过ms，充电机发送SPN3925=01的CEM报文，报文格式、内容和周期GBT 27930—2015中9.5和10.5.2的要求。",
							"en": ""
						}
					]
				},
				{
					"name": "DN3005",
					"id": "DN3005",
					"output_items": [
						{
							"cn": "1 检查充电机判断BCS报文超时时间",
							"en": ""
						},
						{
							"cn": "2 检查SPN3924=01的CEM报文正确性",
							"en": ""
						},
						{
							"cn": "3 检查CEM报文ID正确性",
							"en": ""
						},
						{
							"cn": "4 检查CEM报文发送周期正确性",
							"en": ""
						},
						{
							"cn": "5 检查CEM数据域正确性",
							"en": ""
						},
						{
							"cn": "6 检查CCS报文发送周期正确性",
							"en": ""
						},
						{
							"cn": "7 检查CCS报文发送ID正确性",
							"en": ""
						},
						{
							"cn": "8 检查CCS报文发送长度正确性",
							"en": ""
						},
						{
							"cn": "9 检查CCS报文发送内容正确性",
							"en": ""
						},
						{
							"cn": "1）自上一次接收到BCS报文起ms，充电机发送CCS报文，报文格式、内容和周期GBT 27930—2015中9.3和10.3.3的要求；",
							"en": ""
						},
						{
							"cn": "2）超过ms，充电机发送SPN3924=01的CEM报文，报文格式、内容和周期GBT 27930—2015中9.5和10.5.2的要求。",
							"en": ""
						}
					]
				},
				{
					"name": "DN3006",
					"id": "DN3006",
					"output_items": [
						{
							"cn": "1 检查充电机判断BCL报文超时时间长度",
							"en": ""
						},
						{
							"cn": "2 检查SPN3925=01的CEM报文正确性",
							"en": ""
						},
						{
							"cn": "3 检查CEM报文ID正确性",
							"en": ""
						},
						{
							"cn": "4 检查CEM报文发送周期正确性",
							"en": ""
						},
						{
							"cn": "5 检查CEM数据域正确性",
							"en": ""
						},
						{
							"cn": "6 检查CCS报文发送周期正确性",
							"en": ""
						},
						{
							"cn": "7 检查CCS报文发送ID正确性",
							"en": ""
						},
						{
							"cn": "8 检查CCS报文发送长度正确性",
							"en": ""
						},
						{
							"cn": "9 检查CCS报文发送内容正确性",
							"en": ""
						},
						{
							"cn": "10 检查充电机使用传输协议接收BCS正确性",
							"en": ""
						},
						{
							"cn": "1）充电机传输协议功能接收BCS报文；",
							"en": ""
						},
						{
							"cn": "2）自上一次接收到BCL报文起ms，充电机发送CCS报文，报文格式、内容和周期GBT 27930—2015中9.3和10.3.3的要求；",
							"en": ""
						},
						{
							"cn": "3）超过ms，充电机发送SPN3925=01的CEM报文，报文格式、内容和周期GBT 27930—2015中9.5和10.5.2的要求。",
							"en": ""
						}
					]
				},
				{
					"name": "DN3007",
					"id": "DN3007",
					"output_items": [
						{
							"cn": "1 检查充电机判断BCS报文超时时间",
							"en": ""
						},
						{
							"cn": "2 检查SPN3924=01的CEM报文正确性",
							"en": ""
						},
						{
							"cn": "3 检查CEM报文ID正确性",
							"en": ""
						},
						{
							"cn": "4 检查CEM报文发送周期正确性",
							"en": ""
						},
						{
							"cn": "5 检查CEM数据域正确性",
							"en": ""
						},
						{
							"cn": "6 检查CCS报文发送周期正确性",
							"en": ""
						},
						{
							"cn": "7 检查CCS报文发送ID正确性",
							"en": ""
						},
						{
							"cn": "8 检查CCS报文发送长度正确性",
							"en": ""
						},
						{
							"cn": "9 检查CCS报文发送内容正确性",
							"en": ""
						},
						{
							"cn": "1）自上一次接收到BCS报文起ms内，充电机发送CCS报文，报文格式、内容和周期GBT 27930—2015中9.3和10.3.3的要求；",
							"en": ""
						},
						{
							"cn": "2）超过ms，充电机发送SPN3924=01的CEM报文，报文格式、内容和周期GBT 27930—2015中9.5和10.5.2的要求。",
							"en": ""
						}
					]
				},
				{
					"name": "DN3008",
					"id": "DN3008",
					"output_items": [
						{
							"cn": "1 检查充电机判断BCL报文超时时间",
							"en": ""
						},
						{
							"cn": "2 检查SPN3925=01的CEM报文正确性",
							"en": ""
						},
						{
							"cn": "3 检查CEM报文ID正确性",
							"en": ""
						},
						{
							"cn": "4 检查CEM报文发送周期正确性",
							"en": ""
						},
						{
							"cn": "5 检查CEM数据域正确性",
							"en": ""
						},
						{
							"cn": "6 检查CCS报文发送周期正确性",
							"en": ""
						},
						{
							"cn": "7 检查CCS报文发送ID正确性",
							"en": ""
						},
						{
							"cn": "8 检查CCS报文发送长度正确性",
							"en": ""
						},
						{
							"cn": "9 检查CCS报文发送内容正确性",
							"en": ""
						},
						{
							"cn": "10 检查充电机使用传输协议接收BCS正确性",
							"en": ""
						},
						{
							"cn": "1）充电机传输协议功能接收BCS报文；",
							"en": ""
						},
						{
							"cn": "2）自上一次接收到BCL报文起ms，充电机发送CCS报文，报文格式、内容和周期GBT 27930—2015中9.3和10.3.3的要求；",
							"en": ""
						},
						{
							"cn": "3）超过ms，充电机发送SPN3925=01的CEM报文，报文格式、内容和周期GBT 27930—2015中9.5和10.5.2的要求。",
							"en": ""
						}
					]
				},
				{
					"name": "DN3009",
					"id": "DN3009",
					"output_items": [
						{
							"cn": "1 检查充电机判断BST报文超时时间长度",
							"en": ""
						},
						{
							"cn": "2 检查SPN3926=01的CEM报文正确性",
							"en": ""
						},
						{
							"cn": "3 检查CEM报文ID正确性",
							"en": ""
						},
						{
							"cn": "4 检查CEM报文发送周期正确性",
							"en": ""
						},
						{
							"cn": "5 检查CEM数据域正确性",
							"en": ""
						},
						{
							"cn": "6 检查CST报文发送周期正确性",
							"en": ""
						},
						{
							"cn": "7 检查CST报文发送ID正确性",
							"en": ""
						},
						{
							"cn": "8 检查CST报文发送长度正确性",
							"en": ""
						},
						{
							"cn": "9 检查CST报文发送内容正确性",
							"en": ""
						},
						{
							"cn": "1）自首次发送CST报文起ms，充电机按10 ms的周期发送CST报文，报文格式、内容和周期GBT 27930—2015中9.3和10.3.9的要求；",
							"en": ""
						},
						{
							"cn": "2）超过ms，充电机发送SPN3926=01的CEM报文，报文格式、内容和周期GBT 27930—2015中9.5和10.5.2的要求。",
							"en": ""
						}
					]
				},
				{
					"name": "DN3010",
					"id": "DN3010",
					"output_items": [
						{
							"cn": "1 检查充电机判断BST报文超时时间",
							"en": ""
						},
						{
							"cn": "2 检查SPN3926=01的CEM报文正确性",
							"en": ""
						},
						{
							"cn": "3 检查CEM报文ID正确性",
							"en": ""
						},
						{
							"cn": "4 检查CEM报文发送周期正确性",
							"en": ""
						},
						{
							"cn": "5 检查CEM数据域正确性",
							"en": ""
						},
						{
							"cn": "6 检查CST报文发送周期正确性",
							"en": ""
						},
						{
							"cn": "7 检查CST报文发送ID正确性",
							"en": ""
						},
						{
							"cn": "8 检查CST报文发送长度正确性",
							"en": ""
						},
						{
							"cn": "9 检查CST报文发送内容正确性",
							"en": ""
						},
						{
							"cn": "1）自首次发送CST报文起ms内，充电机按10 ms的周期发送CST报文，报文格式、内容和周期GBT 27930—2015中9.3和10.3.9的要求；",
							"en": ""
						},
						{
							"cn": "2）超过ms，充电机发送SPN3926=01的CEM报文，报文格式、内容和周期GBT 27930—2015中9.5和10.5.2的要求。",
							"en": ""
						}
					]
				}
			]
		},
		{
			"name": "充电结束阶段检验",
			"id": "InspectionAtTheEndOfCharging",
			"experiments": [
				{
					"name": "DP4001",
					"id": "DP4001",
					"output_items": [
						{
							"cn": "1 检查CSD报文ID正确性",
							"en": ""
						},
						{
							"cn": "2 检查CSD报文数据长度正确性",
							"en": ""
						},
						{
							"cn": "3 检查CSD报文发送周期正确性",
							"en": ""
						},
						{
							"cn": "4 检查CSD报文发送中止条件正确性",
							"en": ""
						},
						{
							"cn": "1）充电机250 ms的周期发送CSD报文，报文格式、内容和周期GB/T 27930—2015中9.4和10.4.2的要求，报文长度8个字节；",
							"en": ""
						},
						{
							"cn": "2）充电机停止发送CSD报文，关闭辅助电源，充电结束。",
							"en": ""
						}
					]
				},
				{
					"name": "DP4002",
					"id": "DP4002",
					"output_items": [
						{
							"cn": "1 检查充电机刷卡充电应失败",
							"en": ""
						}
					]
				},
				{
					"name": "DN4001",
					"id": "DN4001",
					"output_items": [
						{
							"cn": "1 检查充电机判断BSD报文超时时间",
							"en": ""
						},
						{
							"cn": "2 检查SPN3927=01的CEM报文正确性",
							"en": ""
						},
						{
							"cn": "3 检查CEM报文ID正确性",
							"en": ""
						},
						{
							"cn": "4 检查CEM报文发送周期正确性",
							"en": ""
						},
						{
							"cn": "5 检查CEM数据域正确性",
							"en": ""
						},
						{
							"cn": "6 检查CST报文发送周期正确性",
							"en": ""
						},
						{
							"cn": "7 检查CST报文发送ID正确性",
							"en": ""
						},
						{
							"cn": "8 检查CST报文发送长度正确性",
							"en": ""
						},
						{
							"cn": "9 检查CST报文发送内容正确性",
							"en": ""
						},
						{
							"cn": "1）自首次发送CST报文起ms充电机10 ms的周期发送CST报文，报文格式、内容和周期GBT 27930—2015中9.3和10.3.9的要求；",
							"en": ""
						},
						{
							"cn": "2）超过m s充电机发送SPN3927=01的CEM报文，报文格式、内容和周期GBT 27930—2015中9.5和10.5.2的要求。",
							"en": ""
						}
					]
				},
				{
					"name": "DN4002",
					"id": "DN4002",
					"output_items": [
						{
							"cn": "1 检查充电机判断BSD超时时间长度",
							"en": ""
						},
						{
							"cn": "2 检查SPN3927=01的CEM报文正确性",
							"en": ""
						},
						{
							"cn": "3 检查CEM报文ID正确性",
							"en": ""
						},
						{
							"cn": "4 检查CEM报文发送周期正确性",
							"en": ""
						},
						{
							"cn": "5 检查CEM数据域正确性",
							"en": ""
						},
						{
							"cn": "6 检查CST报文发送周期正确性",
							"en": ""
						},
						{
							"cn": "7 检查CST报文发送ID正确性",
							"en": ""
						},
						{
							"cn": "8 检查CST报文发送长度正确性",
							"en": ""
						},
						{
							"cn": "9 检查CST报文发送内容正确性",
							"en": ""
						},
						{
							"cn": "1）自首次发送CST报文起ms充电机按10 ms的周期发送CST报文，报文格式、内容和周期GBT 27930—2015中9.3和10.3.9的要求；",
							"en": ""
						},
						{
							"cn": "2）超过ms充电机发送SPN3927=01的CEM报文，报文格式、内容和周期GBT 27930—2015中9.5和10.5.2的要求。",
							"en": ""
						}
					]
				},
				{
					"name": "DN4003",
					"id": "DN4003",
					"output_items": [
						{
							"cn": "1 检查充电机判断BSD超时时间长度",
							"en": ""
						},
						{
							"cn": "2 检查SPN3927=01的CEM报文正确性",
							"en": ""
						},
						{
							"cn": "3 检查CEM报文ID正确性",
							"en": ""
						},
						{
							"cn": "4 检查CEM报文发送周期正确性",
							"en": ""
						},
						{
							"cn": "5 检查CEM数据域正确性",
							"en": ""
						},
						{
							"cn": "6 检查CST报文发送周期正确性",
							"en": ""
						},
						{
							"cn": "7 检查CST报文发送ID正确性",
							"en": ""
						},
						{
							"cn": "8 检查CST报文发送长度正确性",
							"en": ""
						},
						{
							"cn": "9 检查CST报文发送内容正确性",
							"en": ""
						},
						{
							"cn": "1）自首次发送CST报文起ms内充电机10 ms的周期发送CST报文，报文格式、内容和周期GBT 27930—2015中9.3和10.3.9的要求；",
							"en": ""
						},
						{
							"cn": "2）超过ms充电机发送SPN3927=01的CEM报文，报文格式、内容和周期GBT 27930—2015中9.5和10.5.2的要求。",
							"en": ""
						}
					]
				},
				{
					"name": "DN4004",
					"id": "DN4004",
					"output_items": [
						{
							"cn": "1 检查充电机判断BSD超时时间长度",
							"en": ""
						},
						{
							"cn": "2 检查SPN3927=01的CEM报文正确性",
							"en": ""
						},
						{
							"cn": "3 检查CEM报文ID正确性",
							"en": ""
						},
						{
							"cn": "4 检查CEM报文发送周期正确性",
							"en": ""
						},
						{
							"cn": "5 检查CEM数据域正确性",
							"en": ""
						},
						{
							"cn": "6 检查CST报文发送周期正确性",
							"en": ""
						},
						{
							"cn": "7 检查CST报文发送ID正确性",
							"en": ""
						},
						{
							"cn": "8 检查CST报文发送长度正确性",
							"en": ""
						},
						{
							"cn": "9 检查CST报文发送内容正确性",
							"en": ""
						},
						{
							"cn": "1）自首次发送CST报文起ms内充电机10 ms的周期发送CST报文，报文格式、内容和周期GBT 27930—2015中9.3和10.3.9的要求；",
							"en": ""
						},
						{
							"cn": "2）超过m s充电机发送SPN3927=01的CEM报文，报文格式、内容和周期GBT 27930—2015中9.5和10.5.2的要求。",
							"en": ""
						}
					]
				}
			]
		}
	]
}